{
  "cycle_0": [
    {
      "t_ms": 1890716,
      "v": 0.442418
    },
    {
      "t_ms": 1890718,
      "v": 0.551209
    },
    {
      "t_ms": 1890719,
      "v": 0.512527
    },
    {
      "t_ms": 1890721,
      "v": 0.502051
    },
    {
      "t_ms": 1890736,
      "v": 0.791355
    },
    {
      "t_ms": 1890738,
      "v": 0.527839
    },
    {
      "t_ms": 1890739,
      "v": 0.358608
    },
    {
      "t_ms": 1890741,
      "v": 0.076557
    },
    {
      "t_ms": 1890743,
      "v": 0.179707
    },
    {
      "t_ms": 1890745,
      "v": 0.203883
    },
    {
      "t_ms": 1890746,
      "v": 0.302198
    },
    {
      "t_ms": 1890748,
      "v": 0.293333
    },
    {
      "t_ms": 1890750,
      "v": 0.469011
    },
    {
      "t_ms": 1890751,
      "v": 0.552015
    },
    {
      "t_ms": 1890753,
      "v": 0.589084
    },
    {
      "t_ms": 1890755,
      "v": 0.46337
    },
    {
      "t_ms": 1890756,
      "v": 0.308645
    },
    {
      "t_ms": 1890758,
      "v": 0.071722
    },
    {
      "t_ms": 1890760,
      "v": 0.178095
    },
    {
      "t_ms": 1890761,
      "v": 0.205495
    },
    {
      "t_ms": 1890763,
      "v": 0.308645
    },
    {
      "t_ms": 1890765,
      "v": 0.392454
    },
    {
      "t_ms": 1890766,
      "v": 0.55685
    },
    {
      "t_ms": 1890768,
      "v": 0.506081
    },
    {
      "t_ms": 1890770,
      "v": 0.46337
    },
    {
      "t_ms": 1890771,
      "v": 0.378755
    },
    {
      "t_ms": 1890773,
      "v": 0.308645
    },
    {
      "t_ms": 1890775,
      "v": 0.073333
    },
    {
      "t_ms": 1890777,
      "v": 0.179707
    },
    {
      "t_ms": 1890778,
      "v": 0.224835
    },
    {
      "t_ms": 1890780,
      "v": 0.224835
    },
    {
      "t_ms": 1890782,
      "v": 0.411795
    },
    {
      "t_ms": 1890783,
      "v": 0.582637
    },
    {
      "t_ms": 1890785,
      "v": 0.506886
    },
    {
      "t_ms": 1890787,
      "v": 0.460147
    },
    {
      "t_ms": 1890788,
      "v": 0.452088
    },
    {
      "t_ms": 1890790,
      "v": 0.177289
    },
    {
      "t_ms": 1890792,
      "v": 0.153919
    },
    {
      "t_ms": 1890793,
      "v": 0.097509
    },
    {
      "t_ms": 1890795,
      "v": 0.244176
    },
    {
      "t_ms": 1890797,
      "v": 0.334432
    },
    {
      "t_ms": 1890798,
      "v": 0.340879
    },
    {
      "t_ms": 1890800,
      "v": 0.601978
    },
    {
      "t_ms": 1890802,
      "v": 0.514945
    },
    {
      "t_ms": 1890804,
      "v": 0.543956
    },
    {
      "t_ms": 1890805,
      "v": 0.321538
    },
    {
      "t_ms": 1890807,
      "v": 0.228864
    },
    {
      "t_ms": 1890809,
      "v": 0.165201
    },
    {
      "t_ms": 1890810,
      "v": 0.100733
    },
    {
      "t_ms": 1890812,
      "v": 0.17326
    },
    {
      "t_ms": 1890814,
      "v": 0.377143
    },
    {
      "t_ms": 1890815,
      "v": 0.392454
    },
    {
      "t_ms": 1890817,
      "v": 0.531868
    },
    {
      "t_ms": 1890819,
      "v": 0.531062
    },
    {
      "t_ms": 1890821,
      "v": 0.540733
    },
    {
      "t_ms": 1890822,
      "v": 0.395678
    },
    {
      "t_ms": 1890824,
      "v": 0.186154
    },
    {
      "t_ms": 1890826,
      "v": 0.164396
    },
    {
      "t_ms": 1890827,
      "v": 0.101538
    },
    {
      "t_ms": 1890829,
      "v": 0.282857
    },
    {
      "t_ms": 1890831,
      "v": 0.281245
    },
    {
      "t_ms": 1890832,
      "v": 0.526227
    },
    {
      "t_ms": 1890834,
      "v": 0.618095
    },
    {
      "t_ms": 1890836,
      "v": 0.487546
    },
    {
      "t_ms": 1890838,
      "v": 0.505275
    },
    {
      "t_ms": 1890839,
      "v": 0.25707
    },
    {
      "t_ms": 1890841,
      "v": 0.074139
    },
    {
      "t_ms": 1890843,
      "v": 0.082198
    },
    {
      "t_ms": 1890844,
      "v": 0.102344
    },
    {
      "t_ms": 1890846,
      "v": 0.205495
    },
    {
      "t_ms": 1890848,
      "v": 0.308645
    },
    {
      "t_ms": 1890849,
      "v": 0.482711
    },
    {
      "t_ms": 1890851,
      "v": 0.663223
    },
    {
      "t_ms": 1890853,
      "v": 0.592308
    },
    {
      "t_ms": 1890854,
      "v": 0.386007
    },
    {
      "t_ms": 1890856,
      "v": 0.351355
    },
    {
      "t_ms": 1890858,
      "v": 0.074139
    },
    {
      "t_ms": 1890859,
      "v": 0.086227
    },
    {
      "t_ms": 1890861,
      "v": 0.202271
    },
    {
      "t_ms": 1890863,
      "v": 0.302198
    },
    {
      "t_ms": 1890865,
      "v": 0.382784
    },
    {
      "t_ms": 1890866,
      "v": 0.540733
    },
    {
      "t_ms": 1890868,
      "v": 0.514945
    },
    {
      "t_ms": 1890870,
      "v": 0.485934
    },
    {
      "t_ms": 1890871,
      "v": 0.386007
    },
    {
      "t_ms": 1890873,
      "v": 0.334432
    },
    {
      "t_ms": 1890875,
      "v": 0.076557
    },
    {
      "t_ms": 1890876,
      "v": 0.178095
    },
    {
      "t_ms": 1890878,
      "v": 0.205495
    },
    {
      "t_ms": 1890880,
      "v": 0.308645
    },
    {
      "t_ms": 1890881,
      "v": 0.392454
    },
    {
      "t_ms": 1890883,
      "v": 0.456923
    },
    {
      "t_ms": 1890885,
      "v": 0.618095
    },
    {
      "t_ms": 1890886,
      "v": 0.459341
    },
    {
      "t_ms": 1890888,
      "v": 0.461758
    },
    {
      "t_ms": 1890890,
      "v": 0.292527
    },
    {
      "t_ms": 1890891,
      "v": 0.076557
    },
    {
      "t_ms": 1890893,
      "v": 0.089451
    },
    {
      "t_ms": 1890895,
      "v": 0.141026
    },
    {
      "t_ms": 1890896,
      "v": 0.340879
    },
    {
      "t_ms": 1890898,
      "v": 0.319121
    },
    {
      "t_ms": 1890900,
      "v": 0.50044
    },
    {
      "t_ms": 1890901,
      "v": 0.637436
    },
    {
      "t_ms": 1890903,
      "v": 0.553626
    },
    {
      "t_ms": 1890905,
      "v": 0.351355
    },
    {
      "t_ms": 1890906,
      "v": 0.205495
    },
    {
      "t_ms": 1890908,
      "v": 0.153919
    },
    {
      "t_ms": 1890910,
      "v": 0.192601
    },
    {
      "t_ms": 1890911,
      "v": 0.139414
    },
    {
      "t_ms": 1890913,
      "v": 0.334432
    },
    {
      "t_ms": 1890915,
      "v": 0.411795
    },
    {
      "t_ms": 1890917,
      "v": 0.576996
    },
    {
      "t_ms": 1890918,
      "v": 0.604396
    },
    {
      "t_ms": 1890920,
      "v": 0.436777
    },
    {
      "t_ms": 1890922,
      "v": 0.411795
    },
    {
      "t_ms": 1890923,
      "v": 0.153919
    },
    {
      "t_ms": 1890925,
      "v": 0.07011
    },
    {
      "t_ms": 1890927,
      "v": 0.179707
    },
    {
      "t_ms": 1890928,
      "v": 0.240952
    },
    {
      "t_ms": 1890930,
      "v": 0.244176
    },
    {
      "t_ms": 1890932,
      "v": 0.356996
    },
    {
      "t_ms": 1890934,
      "v": 0.618095
    },
    {
      "t_ms": 1890935,
      "v": 0.61326
    },
    {
      "t_ms": 1890937,
      "v": 0.411795
    },
    {
      "t_ms": 1890939,
      "v": 0.411795
    },
    {
      "t_ms": 1890940,
      "v": 0.119267
    },
    {
      "t_ms": 1890942,
      "v": 0.160366
    },
    {
      "t_ms": 1890944,
      "v": 0.189377
    },
    {
      "t_ms": 1890945,
      "v": 0.254652
    },
    {
      "t_ms": 1890947,
      "v": 0.344103
    },
    {
      "t_ms": 1890949,
      "v": 0.460147
    },
    {
      "t_ms": 1890950,
      "v": 0.592308
    },
    {
      "t_ms": 1890952,
      "v": 0.577802
    },
    {
      "t_ms": 1890954,
      "v": 0.405348
    },
    {
      "t_ms": 1890955,
      "v": 0.298168
    },
    {
      "t_ms": 1890957,
      "v": 0.102344
    },
    {
      "t_ms": 1890959,
      "v": 0.160366
    },
    {
      "t_ms": 1890961,
      "v": 0.102344
    },
    {
      "t_ms": 1890962,
      "v": 0.282857
    },
    {
      "t_ms": 1890964,
      "v": 0.269963
    },
    {
      "t_ms": 1890966,
      "v": 0.411795
    },
    {
      "t_ms": 1890967,
      "v": 0.643883
    },
    {
      "t_ms": 1890969,
      "v": 0.510916
    },
    {
      "t_ms": 1890971,
      "v": 0.411795
    },
    {
      "t_ms": 1890972,
      "v": 0.305421
    },
    {
      "t_ms": 1890974,
      "v": 0.176484
    },
    {
      "t_ms": 1890976,
      "v": 0.166813
    },
    {
      "t_ms": 1890977,
      "v": 0.102344
    },
    {
      "t_ms": 1890979,
      "v": 0.200659
    },
    {
      "t_ms": 1890981,
      "v": 0.390037
    },
    {
      "t_ms": 1890983,
      "v": 0.411795
    },
    {
      "t_ms": 1890984,
      "v": 0.551209
    },
    {
      "t_ms": 1890986,
      "v": 0.614066
    },
    {
      "t_ms": 1890988,
      "v": 0.405348
    },
    {
      "t_ms": 1890989,
      "v": 0.384396
    },
    {
      "t_ms": 1890991,
      "v": 0.166007
    },
    {
      "t_ms": 1890993,
      "v": 0.171648
    },
    {
      "t_ms": 1890994,
      "v": 0.19663
    },
    {
      "t_ms": 1890996,
      "v": 0.289304
    },
    {
      "t_ms": 1890998,
      "v": 0.365055
    },
    {
      "t_ms": 1890999,
      "v": 0.411795
    },
    {
      "t_ms": 1891001,
      "v": 0.527839
    },
    {
      "t_ms": 1891003,
      "v": 0.499634
    },
    {
      "t_ms": 1891004,
      "v": 0.405348
    },
    {
      "t_ms": 1891006,
      "v": 0.282857
    },
    {
      "t_ms": 1891008,
      "v": 0.063663
    },
    {
      "t_ms": 1891009,
      "v": 0.166813
    },
    {
      "t_ms": 1891011,
      "v": 0.199048
    },
    {
      "t_ms": 1891013,
      "v": 0.205495
    },
    {
      "t_ms": 1891014,
      "v": 0.395678
    },
    {
      "t_ms": 1891016,
      "v": 0.547179
    },
    {
      "t_ms": 1891018,
      "v": 0.615678
    },
    {
      "t_ms": 1891020,
      "v": 0.462564
    },
    {
      "t_ms": 1891021,
      "v": 0.460952
    },
    {
      "t_ms": 1891023,
      "v": 0.306227
    },
    {
      "t_ms": 1891025,
      "v": 0.073333
    },
    {
      "t_ms": 1891026,
      "v": 0.089451
    },
    {
      "t_ms": 1891028,
      "v": 0.224835
    },
    {
      "t_ms": 1891030,
      "v": 0.308645
    },
    {
      "t_ms": 1891031,
      "v": 0.305421
    },
    {
      "t_ms": 1891033,
      "v": 0.493993
    },
    {
      "t_ms": 1891035,
      "v": 0.630989
    },
    {
      "t_ms": 1891037,
      "v": 0.460952
    },
    {
      "t_ms": 1891038,
      "v": 0.456923
    },
    {
      "t_ms": 1891040,
      "v": 0.279634
    },
    {
      "t_ms": 1891042,
      "v": 0.076557
    },
    {
      "t_ms": 1891043,
      "v": 0.09348
    },
    {
      "t_ms": 1891045,
      "v": 0.237729
    },
    {
      "t_ms": 1891047,
      "v": 0.334432
    },
    {
      "t_ms": 1891048,
      "v": 0.411795
    },
    {
      "t_ms": 1891050,
      "v": 0.487546
    },
    {
      "t_ms": 1891052,
      "v": 0.618095
    },
    {
      "t_ms": 1891054,
      "v": 0.411795
    },
    {
      "t_ms": 1891055,
      "v": 0.411795
    },
    {
      "t_ms": 1891057,
      "v": 0.205495
    },
    {
      "t_ms": 1891059,
      "v": 0.160366
    },
    {
      "t_ms": 1891060,
      "v": 0.102344
    },
    {
      "t_ms": 1891062,
      "v": 0.179707
    },
    {
      "t_ms": 1891064,
      "v": 0.292527
    },
    {
      "t_ms": 1891066,
      "v": 0.411795
    },
    {
      "t_ms": 1891067,
      "v": 0.553626
    },
    {
      "t_ms": 1891069,
      "v": 0.545568
    },
    {
      "t_ms": 1891070,
      "v": 0.456923
    },
    {
      "t_ms": 1891072,
      "v": 0.411795
    },
    {
      "t_ms": 1891074,
      "v": 0.190989
    },
    {
      "t_ms": 1891075,
      "v": 0.069304
    },
    {
      "t_ms": 1891077,
      "v": 0.100733
    },
    {
      "t_ms": 1891079,
      "v": 0.179707
    },
    {
      "t_ms": 1891081,
      "v": 0.289304
    },
    {
      "t_ms": 1891082,
      "v": 0.506081
    },
    {
      "t_ms": 1891084,
      "v": 0.618095
    },
    {
      "t_ms": 1891086,
      "v": 0.508498
    },
    {
      "t_ms": 1891087,
      "v": 0.523004
    },
    {
      "t_ms": 1891089,
      "v": 0.289304
    },
    {
      "t_ms": 1891091,
      "v": 0.09348
    },
    {
      "t_ms": 1891092,
      "v": 0.073333
    },
    {
      "t_ms": 1891094,
      "v": 0.195018
    },
    {
      "t_ms": 1891096,
      "v": 0.269157
    },
    {
      "t_ms": 1891097,
      "v": 0.352161
    },
    {
      "t_ms": 1891099,
      "v": 0.489157
    },
    {
      "t_ms": 1891101,
      "v": 0.514945
    },
    {
      "t_ms": 1891102,
      "v": 0.502051
    },
    {
      "t_ms": 1891104,
      "v": 0.509304
    },
    {
      "t_ms": 1891106,
      "v": 0.27641
    },
    {
      "t_ms": 1891108,
      "v": 0.076557
    },
    {
      "t_ms": 1891109,
      "v": 0.083004
    },
    {
      "t_ms": 1891111,
      "v": 0.199048
    },
    {
      "t_ms": 1891113,
      "v": 0.282857
    },
    {
      "t_ms": 1891114,
      "v": 0.269963
    },
    {
      "t_ms": 1891116,
      "v": 0.444029
    },
    {
      "t_ms": 1891118,
      "v": 0.637436
    },
    {
      "t_ms": 1891119,
      "v": 0.494799
    },
    {
      "t_ms": 1891121,
      "v": 0.489157
    },
    {
      "t_ms": 1891123,
      "v": 0.351355
    },
    {
      "t_ms": 1891124,
      "v": 0.168425
    },
    {
      "t_ms": 1891126,
      "v": 0.174066
    },
    {
      "t_ms": 1891128,
      "v": 0.112821
    },
    {
      "t_ms": 1891130,
      "v": 0.321538
    },
    {
      "t_ms": 1891131,
      "v": 0.307839
    },
    {
      "t_ms": 1891133,
      "v": 0.56652
    },
    {
      "t_ms": 1891135,
      "v": 0.618095
    },
    {
      "t_ms": 1891136,
      "v": 0.560073
    },
    {
      "t_ms": 1891138,
      "v": 0.356996
    },
    {
      "t_ms": 1891140,
      "v": 0.224835
    },
    {
      "t_ms": 1891141,
      "v": 0.07011
    },
    {
      "t_ms": 1891143,
      "v": 0.178901
    },
    {
      "t_ms": 1891145,
      "v": 0.12652
    },
    {
      "t_ms": 1891146,
      "v": 0.244176
    },
    {
      "t_ms": 1891148,
      "v": 0.411795
    },
    {
      "t_ms": 1891150,
      "v": 0.583443
    },
    {
      "t_ms": 1891151,
      "v": 0.611648
    },
    {
      "t_ms": 1891153,
      "v": 0.450476
    },
    {
      "t_ms": 1891155,
      "v": 0.36022
    },
    {
      "t_ms": 1891157,
      "v": 0.204689
    },
    {
      "t_ms": 1891158,
      "v": 0.07011
    },
    {
      "t_ms": 1891160,
      "v": 0.179707
    },
    {
      "t_ms": 1891162,
      "v": 0.141026
    },
    {
      "t_ms": 1891163,
      "v": 0.256264
    },
    {
      "t_ms": 1891165,
      "v": 0.356996
    },
    {
      "t_ms": 1891167,
      "v": 0.618095
    },
    {
      "t_ms": 1891168,
      "v": 0.618095
    },
    {
      "t_ms": 1891170,
      "v": 0.537509
    },
    {
      "t_ms": 1891172,
      "v": 0.334432
    },
    {
      "t_ms": 1891173,
      "v": 0.153919
    },
    {
      "t_ms": 1891175,
      "v": 0.153919
    },
    {
      "t_ms": 1891177,
      "v": 0.09348
    },
    {
      "t_ms": 1891179,
      "v": 0.16359
    },
    {
      "t_ms": 1891180,
      "v": 0.36022
    },
    {
      "t_ms": 1891182,
      "v": 0.366667
    },
    {
      "t_ms": 1891184,
      "v": 0.549597
    },
    {
      "t_ms": 1891185,
      "v": 0.618095
    },
    {
      "t_ms": 1891187,
      "v": 0.441612
    },
    {
      "t_ms": 1891189,
      "v": 0.338462
    },
    {
      "t_ms": 1891190,
      "v": 0.132161
    },
    {
      "t_ms": 1891192,
      "v": 0.164396
    },
    {
      "t_ms": 1891194,
      "v": 0.186154
    },
    {
      "t_ms": 1891195,
      "v": 0.153919
    },
    {
      "t_ms": 1891197,
      "v": 0.267546
    },
    {
      "t_ms": 1891199,
      "v": 0.395678
    },
    {
      "t_ms": 1891200,
      "v": 0.552821
    },
    {
      "t_ms": 1891202,
      "v": 0.630989
    },
    {
      "t_ms": 1891204,
      "v": 0.527839
    },
    {
      "t_ms": 1891205,
      "v": 0.390842
    },
    {
      "t_ms": 1891207,
      "v": 0.179707
    },
    {
      "t_ms": 1891209,
      "v": 0.083004
    },
    {
      "t_ms": 1891210,
      "v": 0.186154
    },
    {
      "t_ms": 1891212,
      "v": 0.25707
    },
    {
      "t_ms": 1891214,
      "v": 0.263516
    },
    {
      "t_ms": 1891216,
      "v": 0.411795
    },
    {
      "t_ms": 1891217,
      "v": 0.641465
    },
    {
      "t_ms": 1891219,
      "v": 0.505275
    },
    {
      "t_ms": 1891221,
      "v": 0.514945
    },
    {
      "t_ms": 1891222,
      "v": 0.282857
    },
    {
      "t_ms": 1891224,
      "v": 0.087033
    },
    {
      "t_ms": 1891226,
      "v": 0.166007
    },
    {
      "t_ms": 1891227,
      "v": 0.102344
    },
    {
      "t_ms": 1891229,
      "v": 0.289304
    },
    {
      "t_ms": 1891231,
      "v": 0.366667
    },
    {
      "t_ms": 1891232,
      "v": 0.511722
    },
    {
      "t_ms": 1891234,
      "v": 0.514945
    },
    {
      "t_ms": 1891236,
      "v": 0.587472
    },
    {
      "t_ms": 1891238,
      "v": 0.385201
    },
    {
      "t_ms": 1891239,
      "v": 0.353773
    },
    {
      "t_ms": 1891241,
      "v": 0.076557
    },
    {
      "t_ms": 1891243,
      "v": 0.087839
    },
    {
      "t_ms": 1891244,
      "v": 0.115238
    },
    {
      "t_ms": 1891246,
      "v": 0.231282
    },
    {
      "t_ms": 1891248,
      "v": 0.325568
    },
    {
      "t_ms": 1891249,
      "v": 0.57619
    },
    {
      "t_ms": 1891251,
      "v": 0.547179
    },
    {
      "t_ms": 1891253,
      "v": 0.495604
    },
    {
      "t_ms": 1891255,
      "v": 0.398901
    },
    {
      "t_ms": 1891256,
      "v": 0.347326
    },
    {
      "t_ms": 1891258,
      "v": 0.166813
    },
    {
      "t_ms": 1891260,
      "v": 0.083004
    },
    {
      "t_ms": 1891261,
      "v": 0.205495
    },
    {
      "t_ms": 1891263,
      "v": 0.318315
    },
    {
      "t_ms": 1891265,
      "v": 0.398901
    },
    {
      "t_ms": 1891266,
      "v": 0.56652
    },
    {
      "t_ms": 1891268,
      "v": 0.503663
    },
    {
      "t_ms": 1891270,
      "v": 0.547985
    },
    {
      "t_ms": 1891272,
      "v": 0.411795
    },
    {
      "t_ms": 1891273,
      "v": 0.166007
    },
    {
      "t_ms": 1891275,
      "v": 0.068498
    },
    {
      "t_ms": 1891277,
      "v": 0.092674
    },
    {
      "t_ms": 1891278,
      "v": 0.244176
    },
    {
      "t_ms": 1891280,
      "v": 0.249817
    },
    {
      "t_ms": 1891282,
      "v": 0.36022
    },
    {
      "t_ms": 1891283,
      "v": 0.532674
    },
    {
      "t_ms": 1891285,
      "v": 0.637436
    },
    {
      "t_ms": 1891287,
      "v": 0.540733
    },
    {
      "t_ms": 1891288,
      "v": 0.411795
    },
    {
      "t_ms": 1891290,
      "v": 0.133773
    },
    {
      "t_ms": 1891292,
      "v": 0.153919
    },
    {
      "t_ms": 1891294,
      "v": 0.186154
    },
    {
      "t_ms": 1891295,
      "v": 0.16359
    },
    {
      "t_ms": 1891297,
      "v": 0.36022
    },
    {
      "t_ms": 1891299,
      "v": 0.386007
    },
    {
      "t_ms": 1891300,
      "v": 0.637436
    },
    {
      "t_ms": 1891302,
      "v": 0.601172
    },
    {
      "t_ms": 1891304,
      "v": 0.502051
    },
    {
      "t_ms": 1891306,
      "v": 0.37956
    },
    {
      "t_ms": 1891307,
      "v": 0.17326
    },
    {
      "t_ms": 1891309,
      "v": 0.076557
    },
    {
      "t_ms": 1891311,
      "v": 0.192601
    },
    {
      "t_ms": 1891312,
      "v": 0.185348
    },
    {
      "t_ms": 1891314,
      "v": 0.373114
    },
    {
      "t_ms": 1891316,
      "v": 0.411795
    },
    {
      "t_ms": 1891317,
      "v": 0.551209
    },
    {
      "t_ms": 1891319,
      "v": 0.607619
    },
    {
      "t_ms": 1891321,
      "v": 0.408571
    },
    {
      "t_ms": 1891322,
      "v": 0.385201
    },
    {
      "t_ms": 1891324,
      "v": 0.076557
    },
    {
      "t_ms": 1891326,
      "v": 0.17326
    },
    {
      "t_ms": 1891328,
      "v": 0.199048
    },
    {
      "t_ms": 1891329,
      "v": 0.282051
    },
    {
      "t_ms": 1891331,
      "v": 0.36022
    },
    {
      "t_ms": 1891333,
      "v": 0.411795
    },
    {
      "t_ms": 1891334,
      "v": 0.534286
    },
    {
      "t_ms": 1891336,
      "v": 0.501245
    },
    {
      "t_ms": 1891338,
      "v": 0.495604
    },
    {
      "t_ms": 1891339,
      "v": 0.34652
    },
    {
      "t_ms": 1891341,
      "v": 0.166813
    },
    {
      "t_ms": 1891343,
      "v": 0.178095
    },
    {
      "t_ms": 1891344,
      "v": 0.200659
    },
    {
      "t_ms": 1891346,
      "v": 0.302198
    },
    {
      "t_ms": 1891348,
      "v": 0.289304
    },
    {
      "t_ms": 1891350,
      "v": 0.47304
    },
    {
      "t_ms": 1891351,
      "v": 0.639048
    },
    {
      "t_ms": 1891353,
      "v": 0.475458
    },
    {
      "t_ms": 1891355,
      "v": 0.472234
    },
    {
      "t_ms": 1891356,
      "v": 0.228864
    },
    {
      "t_ms": 1891358,
      "v": 0.153919
    },
    {
      "t_ms": 1891360,
      "v": 0.177289
    },
    {
      "t_ms": 1891361,
      "v": 0.121685
    },
    {
      "t_ms": 1891363,
      "v": 0.237729
    },
    {
      "t_ms": 1891365,
      "v": 0.334432
    },
    {
      "t_ms": 1891366,
      "v": 0.507692
    },
    {
      "t_ms": 1891368,
      "v": 0.56652
    },
    {
      "t_ms": 1891370,
      "v": 0.592308
    },
    {
      "t_ms": 1891371,
      "v": 0.46337
    },
    {
      "t_ms": 1891373,
      "v": 0.205495
    },
    {
      "t_ms": 1891375,
      "v": 0.073333
    },
    {
      "t_ms": 1891376,
      "v": 0.09348
    },
    {
      "t_ms": 1891378,
      "v": 0.145055
    },
    {
      "t_ms": 1891380,
      "v": 0.348938
    },
    {
      "t_ms": 1891382,
      "v": 0.334432
    },
    {
      "t_ms": 1891383,
      "v": 0.596337
    },
    {
      "t_ms": 1891385,
      "v": 0.53348
    },
    {
      "t_ms": 1891387,
      "v": 0.460952
    },
    {
      "t_ms": 1891388,
      "v": 0.365861
    },
    {
      "t_ms": 1891390,
      "v": 0.179707
    },
    {
      "t_ms": 1891392,
      "v": 0.160366
    },
    {
      "t_ms": 1891394,
      "v": 0.099121
    },
    {
      "t_ms": 1891395,
      "v": 0.253846
    },
    {
      "t_ms": 1891397,
      "v": 0.347326
    },
    {
      "t_ms": 1891399,
      "v": 0.448864
    },
    {
      "t_ms": 1891400,
      "v": 0.499634
    },
    {
      "t_ms": 1891402,
      "v": 0.605201
    },
    {
      "t_ms": 1891404,
      "v": 0.514945
    },
    {
      "t_ms": 1891405,
      "v": 0.308645
    },
    {
      "t_ms": 1891407,
      "v": 0.205495
    },
    {
      "t_ms": 1891409,
      "v": 0.166813
    },
    {
      "t_ms": 1891410,
      "v": 0.100733
    },
    {
      "t_ms": 1891412,
      "v": 0.166813
    },
    {
      "t_ms": 1891414,
      "v": 0.282857
    },
    {
      "t_ms": 1891415,
      "v": 0.50044
    },
    {
      "t_ms": 1891417,
      "v": 0.527839
    },
    {
      "t_ms": 1891419,
      "v": 0.618095
    },
    {
      "t_ms": 1891421,
      "v": 0.514945
    },
    {
      "t_ms": 1891422,
      "v": 0.302198
    },
    {
      "t_ms": 1891424,
      "v": 0.100733
    },
    {
      "t_ms": 1891426,
      "v": 0.076557
    },
    {
      "t_ms": 1891427,
      "v": 0.102344
    },
    {
      "t_ms": 1891429,
      "v": 0.199048
    },
    {
      "t_ms": 1891431,
      "v": 0.390842
    },
    {
      "t_ms": 1891432,
      "v": 0.411795
    },
    {
      "t_ms": 1891434,
      "v": 0.546374
    },
    {
      "t_ms": 1891436,
      "v": 0.612454
    },
    {
      "t_ms": 1891437,
      "v": 0.411795
    },
    {
      "t_ms": 1891439,
      "v": 0.40293
    },
    {
      "t_ms": 1891441,
      "v": 0.083004
    },
    {
      "t_ms": 1891442,
      "v": 0.076557
    },
    {
      "t_ms": 1891444,
      "v": 0.102344
    },
    {
      "t_ms": 1891446,
      "v": 0.205495
    },
    {
      "t_ms": 1891447,
      "v": 0.305421
    },
    {
      "t_ms": 1891449,
      "v": 0.450476
    },
    {
      "t_ms": 1891451,
      "v": 0.564103
    },
    {
      "t_ms": 1891452,
      "v": 0.530256
    },
    {
      "t_ms": 1891454,
      "v": 0.527033
    },
    {
      "t_ms": 1891456,
      "v": 0.37956
    },
    {
      "t_ms": 1891458,
      "v": 0.075751
    },
    {
      "t_ms": 1891459,
      "v": 0.166813
    },
    {
      "t_ms": 1891461,
      "v": 0.102344
    },
    {
      "t_ms": 1891463,
      "v": 0.205495
    },
    {
      "t_ms": 1891464,
      "v": 0.308645
    },
    {
      "t_ms": 1891466,
      "v": 0.56652
    },
    {
      "t_ms": 1891468,
      "v": 0.63663
    },
    {
      "t_ms": 1891469,
      "v": 0.574579
    },
    {
      "t_ms": 1891471,
      "v": 0.459341
    },
    {
      "t_ms": 1891473,
      "v": 0.308645
    },
    {
      "t_ms": 1891474,
      "v": 0.072527
    },
    {
      "t_ms": 1891476,
      "v": 0.172454
    },
    {
      "t_ms": 1891478,
      "v": 0.203883
    },
    {
      "t_ms": 1891480,
      "v": 0.205495
    },
    {
      "t_ms": 1891481,
      "v": 0.407766
    },
    {
      "t_ms": 1891483,
      "v": 0.560073
    },
    {
      "t_ms": 1891485,
      "v": 0.616484
    },
    {
      "t_ms": 1891486,
      "v": 0.454505
    },
    {
      "t_ms": 1891488,
      "v": 0.368278
    },
    {
      "t_ms": 1891490,
      "v": 0.228059
    },
    {
      "t_ms": 1891491,
      "v": 0.153919
    },
    {
      "t_ms": 1891493,
      "v": 0.095092
    },
    {
      "t_ms": 1891495,
      "v": 0.230476
    },
    {
      "t_ms": 1891497,
      "v": 0.326374
    },
    {
      "t_ms": 1891498,
      "v": 0.308645
    },
    {
      "t_ms": 1891500,
      "v": 0.502051
    },
    {
      "t_ms": 1891502,
      "v": 0.545568
    },
    {
      "t_ms": 1891503,
      "v": 0.56652
    },
    {
      "t_ms": 1891505,
      "v": 0.447253
    },
    {
      "t_ms": 1891507,
      "v": 0.269963
    },
    {
      "t_ms": 1891508,
      "v": 0.073333
    },
    {
      "t_ms": 1891510,
      "v": 0.179707
    },
    {
      "t_ms": 1891511,
      "v": 0.13619
    },
    {
      "t_ms": 1891513,
      "v": 0.250623
    },
    {
      "t_ms": 1891515,
      "v": 0.353773
    },
    {
      "t_ms": 1891517,
      "v": 0.527839
    },
    {
      "t_ms": 1891518,
      "v": 0.653553
    },
    {
      "t_ms": 1891520,
      "v": 0.469817
    },
    {
      "t_ms": 1891522,
      "v": 0.368278
    },
    {
      "t_ms": 1891523,
      "v": 0.263516
    },
    {
      "t_ms": 1891525,
      "v": 0.160366
    },
    {
      "t_ms": 1891527,
      "v": 0.098315
    },
    {
      "t_ms": 1891528,
      "v": 0.241758
    },
    {
      "t_ms": 1891530,
      "v": 0.231282
    },
    {
      "t_ms": 1891532,
      "v": 0.352967
    },
    {
      "t_ms": 1891533,
      "v": 0.610842
    },
    {
      "t_ms": 1891535,
      "v": 0.527839
    },
    {
      "t_ms": 1891537,
      "v": 0.460952
    },
    {
      "t_ms": 1891538,
      "v": 0.366667
    },
    {
      "t_ms": 1891540,
      "v": 0.177289
    },
    {
      "t_ms": 1891542,
      "v": 0.083004
    },
    {
      "t_ms": 1891544,
      "v": 0.099121
    },
    {
      "t_ms": 1891545,
      "v": 0.25707
    },
    {
      "t_ms": 1891547,
      "v": 0.347326
    },
    {
      "t_ms": 1891549,
      "v": 0.448059
    },
    {
      "t_ms": 1891550,
      "v": 0.495604
    },
    {
      "t_ms": 1891552,
      "v": 0.604396
    },
    {
      "t_ms": 1891554,
      "v": 0.411795
    },
    {
      "t_ms": 1891555,
      "v": 0.308645
    },
    {
      "t_ms": 1891557,
      "v": 0.199048
    },
    {
      "t_ms": 1891559,
      "v": 0.160366
    },
    {
      "t_ms": 1891561,
      "v": 0.102344
    },
    {
      "t_ms": 1891562,
      "v": 0.28044
    },
    {
      "t_ms": 1891564,
      "v": 0.26674
    },
    {
      "t_ms": 1891566,
      "v": 0.514139
    },
    {
      "t_ms": 1891567,
      "v": 0.618095
    },
    {
      "t_ms": 1891569,
      "v": 0.572967
    },
    {
      "t_ms": 1891571,
      "v": 0.390842
    },
    {
      "t_ms": 1893667,
      "v": 0.705128
    }
  ]
}